molfeat_hype/__init__.py
molfeat_hype/memory.py
molfeat_hype/utils.py
molfeat_hype/trans/__init__.py
molfeat_hype/trans/llm_embeddings.py
molfeat_hype/trans/llm_instruct_embeddings.py
molfeat_hype-0.1.0.dist-info/LICENSE
molfeat_hype-0.1.0.dist-info/METADATA
molfeat_hype-0.1.0.dist-info/WHEEL
molfeat_hype-0.1.0.dist-info/entry_points.txt
molfeat_hype-0.1.0.dist-info/top_level.txt
molfeat_hype-0.1.0.dist-info/RECORD
