Metadata-Version: 2.1
Name: molfeat-hype
Version: 0.1.0
Summary: molfeat plugin that leverages the most hyped LLM models in NLP for molecular featurization
Author-email: Emmanuel Noutahi <emmanuel.noutahi@hotmail.ca>
License: Apache-2.0
Project-URL: Website, https://molfeat.datamol.io
Project-URL: Source Code, https://github.com/maclandrol/molfeat-hype
Project-URL: Bug Tracker, https://github.com/maclandrol/molfeat-hype/issues
Project-URL: Documentation, https://molfeat-docs.datamol.io
Keywords: molfeat,chatGPT,LLM,llama,alpaca
Classifier: Development Status :: 3 - Alpha
Classifier: Intended Audience :: Developers
Classifier: Intended Audience :: Healthcare Industry
Classifier: Intended Audience :: Science/Research
Classifier: Topic :: Scientific/Engineering :: Artificial Intelligence
Classifier: Topic :: Scientific/Engineering :: Bio-Informatics
Classifier: Topic :: Scientific/Engineering :: Information Analysis
Classifier: Topic :: Scientific/Engineering :: Medical Science Apps.
Classifier: Natural Language :: English
Classifier: Operating System :: OS Independent
Classifier: Programming Language :: Python
Classifier: Programming Language :: Python :: 3
Classifier: Programming Language :: Python :: 3.8
Classifier: Programming Language :: Python :: 3.9
Classifier: Programming Language :: Python :: 3.10
Requires-Python: >=3.8
License-File: LICENSE
Requires-Dist: datamol
Requires-Dist: molfeat
Requires-Dist: langchain
Requires-Dist: InstructorEmbedding
Requires-Dist: transformers
Requires-Dist: sentence-transformers
Requires-Dist: openai
Requires-Dist: python-dotenv
